postman/__init__.py
postman/admin.py
postman/api.py
postman/api_urls.py
postman/api_views.py
postman/apps.py
postman/context_processors.py
postman/fields.py
postman/forms.py
postman/models.py
postman/module_for_tests.py
postman/query.py
postman/tests.py
postman/urls.py
postman/urls_for_tests.py
postman/utils.py
postman/views.py
postman/locale/ar/LC_MESSAGES/django.mo
postman/locale/ar/LC_MESSAGES/django.po
postman/locale/cs/LC_MESSAGES/django.mo
postman/locale/cs/LC_MESSAGES/django.po
postman/locale/da/LC_MESSAGES/django.mo
postman/locale/da/LC_MESSAGES/django.po
postman/locale/de/LC_MESSAGES/django.mo
postman/locale/de/LC_MESSAGES/django.po
postman/locale/el/LC_MESSAGES/django.mo
postman/locale/el/LC_MESSAGES/django.po
postman/locale/en/LC_MESSAGES/django.mo
postman/locale/en/LC_MESSAGES/django.po
postman/locale/eo/LC_MESSAGES/django.mo
postman/locale/eo/LC_MESSAGES/django.po
postman/locale/es/LC_MESSAGES/django.mo
postman/locale/es/LC_MESSAGES/django.po
postman/locale/fa_IR/LC_MESSAGES/django.mo
postman/locale/fa_IR/LC_MESSAGES/django.po
postman/locale/fr/LC_MESSAGES/django.mo
postman/locale/fr/LC_MESSAGES/django.po
postman/locale/hu/LC_MESSAGES/django.mo
postman/locale/hu/LC_MESSAGES/django.po
postman/locale/it/LC_MESSAGES/django.mo
postman/locale/it/LC_MESSAGES/django.po
postman/locale/ka/LC_MESSAGES/django.mo
postman/locale/ka/LC_MESSAGES/django.po
postman/locale/lv/LC_MESSAGES/django.mo
postman/locale/lv/LC_MESSAGES/django.po
postman/locale/nl/LC_MESSAGES/django.mo
postman/locale/nl/LC_MESSAGES/django.po
postman/locale/pl/LC_MESSAGES/django.mo
postman/locale/pl/LC_MESSAGES/django.po
postman/locale/pt_BR/LC_MESSAGES/django.mo
postman/locale/pt_BR/LC_MESSAGES/django.po
postman/locale/ru/LC_MESSAGES/django.mo
postman/locale/ru/LC_MESSAGES/django.po
postman/locale/sl_SI/LC_MESSAGES/django.mo
postman/locale/sl_SI/LC_MESSAGES/django.po
postman/locale/th_TH/LC_MESSAGES/django.mo
postman/locale/th_TH/LC_MESSAGES/django.po
postman/locale/tr/LC_MESSAGES/django.mo
django_postman-4.4.dist-info/LICENSE
django_postman-4.4.dist-info/METADATA
django_postman-4.4.dist-info/WHEEL
django_postman-4.4.dist-info/top_level.txt
django_postman-4.4.dist-info/RECORD
