Metadata-Version: 2.1
Name: django-postman
Version: 4.4
Summary: User-to-User messaging system for Django, with gateway to AnonymousUser, moderation and thread management, user & exchange filters, inbox/sent/archives/trash folders, support for apps: auto-complete, notification, mailer.
Author-email: Patrick Samson <maxcom@laposte.net>
License: Copyright (c) 2010, Patrick Samson.
Project-URL: Repository, https://bitbucket.org/psam/django-postman
Keywords: django,messages,messaging,email,moderation
Classifier: Development Status :: 5 - Production/Stable
Classifier: Environment :: Web Environment
Classifier: Framework :: Django
Classifier: Intended Audience :: Developers
Classifier: License :: OSI Approved :: BSD License
Classifier: Operating System :: OS Independent
Classifier: Programming Language :: Python
Classifier: Programming Language :: Python :: 3
Classifier: Programming Language :: Python :: 3 :: Only
Classifier: Topic :: Communications :: Email
License-File: LICENSE
Requires-Dist: Django
